marina/__init__.py
marina/build.py
marina/cli.py
marina/compat.py
marina/utils.py
marina-0.4.3.dist-info/METADATA
marina-0.4.3.dist-info/WHEEL
marina-0.4.3.dist-info/entry_points.txt
marina-0.4.3.dist-info/top_level.txt
marina-0.4.3.dist-info/RECORD
