Metadata-Version: 2.1
Name: marina
Version: 0.4.3
Summary: marina manages docker instances
Home-page: https://github.com/mmerickel/marina
Author: Michael Merickel
Author-email: oss@m.merickel.org
License: UNKNOWN
Keywords: docker devops deploy build orchestration
Platform: UNKNOWN
Classifier: Development Status :: 4 - Beta
Classifier: Intended Audience :: Developers
Classifier: Intended Audience :: System Administrators
Classifier: Programming Language :: Python
Classifier: Topic :: System :: Installation/Setup
Classifier: Topic :: System :: Software Distribution
Classifier: Topic :: System :: Systems Administration
Requires-Dist: docker (>=3.0)
Requires-Dist: PyYAML
Requires-Dist: setuptools
Requires-Dist: subparse
Provides-Extra: testing
Requires-Dist: pytest ; extra == 'testing'
